sanduuzlogformatter/__init__.py
sanduuzlogformatter/sanduuzlogformatter.py
sanduuzlogformatter-1.0.2.dist-info/LICENSE
sanduuzlogformatter-1.0.2.dist-info/METADATA
sanduuzlogformatter-1.0.2.dist-info/WHEEL
sanduuzlogformatter-1.0.2.dist-info/top_level.txt
sanduuzlogformatter-1.0.2.dist-info/RECORD
