Metadata-Version: 2.1
Name: sanduuzlogformatter
Version: 1.0.2
Summary: Sanduuz Log Formatter (SLF) is a custom log formatter for the python logging library
Author-email: Santtu Sievänen <sanduuz@iki.fi>
Project-URL: Homepage, https://github.com/Sanduuz/SanduuzLogFormatter
Project-URL: Issues, https://github.com/Sanduuz/SanduuzLogFormatter/issues
Classifier: Programming Language :: Python :: 3
Classifier: Operating System :: OS Independent
Requires-Python: >=3.8
License-File: LICENSE
